{
  "formId": "f8812",
  "displayName": "Form 8812",
  "taxYear": 2024,
  "sourceUrl": "https://www.irs.gov/pub/irs-pdf/f8812.pdf",
  "generatedAt": "2026-04-07T00:27:44.466Z",
  "fields": [
    {
      "pdfFieldName": "topmostSubform[0].Page1[0].p1-t1[0]",
      "fieldType": "generic_text",
      "labelHint": "Text Field",
      "required": false
    },
    {
      "pdfFieldName": "topmostSubform[0].Page1[0].p1-t4[0]",
      "fieldType": "generic_text",
      "labelHint": "Text Field",
      "required": false,
      "maxLength": 11
    },
    {
      "pdfFieldName": "topmostSubform[0].Page1[0].p1-t5[0]",
      "fieldType": "generic_text",
      "labelHint": "Text Field",
      "required": false
    },
    {
      "pdfFieldName": "topmostSubform[0].Page1[0].p1-t6[0]",
      "fieldType": "generic_text",
      "labelHint": "Text Field",
      "required": false,
      "maxLength": 3
    },
    {
      "pdfFieldName": "topmostSubform[0].Page1[0].p1-t7[0]",
      "fieldType": "generic_text",
      "labelHint": "Text Field",
      "required": false
    },
    {
      "pdfFieldName": "topmostSubform[0].Page1[0].p1-t8[0]",
      "fieldType": "generic_text",
      "labelHint": "Text Field",
      "required": false,
      "maxLength": 3
    },
    {
      "pdfFieldName": "topmostSubform[0].Page1[0].p1-t9[0]",
      "fieldType": "generic_text",
      "labelHint": "Text Field",
      "required": false
    },
    {
      "pdfFieldName": "topmostSubform[0].Page1[0].p1-t10[0]",
      "fieldType": "generic_text",
      "labelHint": "Text Field",
      "required": false,
      "maxLength": 3
    },
    {
      "pdfFieldName": "topmostSubform[0].Page1[0].p1-t11[0]",
      "fieldType": "generic_text",
      "labelHint": "Text Field",
      "required": false
    },
    {
      "pdfFieldName": "topmostSubform[0].Page1[0].p1-t12[0]",
      "fieldType": "generic_text",
      "labelHint": "Text Field",
      "required": false,
      "maxLength": 3
    },
    {
      "pdfFieldName": "topmostSubform[0].Page1[0].p1-t13[0]",
      "fieldType": "generic_text",
      "labelHint": "Text Field",
      "required": false
    },
    {
      "pdfFieldName": "topmostSubform[0].Page1[0].p1-t14[0]",
      "fieldType": "generic_text",
      "labelHint": "Text Field",
      "required": false,
      "maxLength": 3
    },
    {
      "pdfFieldName": "topmostSubform[0].Page1[0].p1-t15[0]",
      "fieldType": "generic_text",
      "labelHint": "Text Field",
      "required": false
    },
    {
      "pdfFieldName": "topmostSubform[0].Page1[0].p1-t16[0]",
      "fieldType": "generic_text",
      "labelHint": "Text Field",
      "required": false,
      "maxLength": 3
    },
    {
      "pdfFieldName": "topmostSubform[0].Page1[0].p1-t17[0]",
      "fieldType": "generic_text",
      "labelHint": "Text Field",
      "required": false
    },
    {
      "pdfFieldName": "topmostSubform[0].Page1[0].p1-t18[0]",
      "fieldType": "generic_text",
      "labelHint": "Text Field",
      "required": false,
      "maxLength": 3
    },
    {
      "pdfFieldName": "topmostSubform[0].Page1[0].p1-t19[0]",
      "fieldType": "generic_text",
      "labelHint": "Text Field",
      "required": false
    },
    {
      "pdfFieldName": "topmostSubform[0].Page1[0].p1-t20[0]",
      "fieldType": "generic_text",
      "labelHint": "Text Field",
      "required": false,
      "maxLength": 3
    },
    {
      "pdfFieldName": "topmostSubform[0].Page1[0].p1-t21[0]",
      "fieldType": "generic_text",
      "labelHint": "Text Field",
      "required": false
    },
    {
      "pdfFieldName": "topmostSubform[0].Page1[0].p1-t22[0]",
      "fieldType": "generic_text",
      "labelHint": "Text Field",
      "required": false,
      "maxLength": 3
    },
    {
      "pdfFieldName": "topmostSubform[0].Page1[0].p1-t23[0]",
      "fieldType": "generic_text",
      "labelHint": "Text Field",
      "required": false
    },
    {
      "pdfFieldName": "topmostSubform[0].Page1[0].p1-t24[0]",
      "fieldType": "generic_text",
      "labelHint": "Text Field",
      "required": false,
      "maxLength": 3
    },
    {
      "pdfFieldName": "topmostSubform[0].Page1[0].p1-t25[0]",
      "fieldType": "generic_text",
      "labelHint": "Text Field",
      "required": false
    },
    {
      "pdfFieldName": "topmostSubform[0].Page1[0].p1-t26[0]",
      "fieldType": "generic_text",
      "labelHint": "Text Field",
      "required": false,
      "maxLength": 3
    },
    {
      "pdfFieldName": "topmostSubform[0].Page1[0].p1-t27[0]",
      "fieldType": "generic_text",
      "labelHint": "Text Field",
      "required": false
    },
    {
      "pdfFieldName": "topmostSubform[0].Page1[0].p1-t28[0]",
      "fieldType": "generic_text",
      "labelHint": "Text Field",
      "required": false,
      "maxLength": 3
    },
    {
      "pdfFieldName": "topmostSubform[0].Page1[0].p1-t29[0]",
      "fieldType": "generic_text",
      "labelHint": "Text Field",
      "required": false
    },
    {
      "pdfFieldName": "topmostSubform[0].Page1[0].p1-t30[0]",
      "fieldType": "generic_text",
      "labelHint": "Text Field",
      "required": false,
      "maxLength": 3
    },
    {
      "pdfFieldName": "topmostSubform[0].Page1[0].p1-t31[0]",
      "fieldType": "generic_text",
      "labelHint": "Text Field",
      "required": false
    },
    {
      "pdfFieldName": "topmostSubform[0].Page1[0].p1-t32[0]",
      "fieldType": "generic_text",
      "labelHint": "Text Field",
      "required": false,
      "maxLength": 3
    },
    {
      "pdfFieldName": "topmostSubform[0].Page1[0].p2-cb2",
      "fieldType": "checkbox",
      "labelHint": "Checkbox",
      "required": false,
      "options": [
        "Yes",
        "Off"
      ]
    },
    {
      "pdfFieldName": "topmostSubform[0].Page1[0].p2-cb4",
      "fieldType": "checkbox",
      "labelHint": "Checkbox",
      "required": false,
      "options": [
        "Yes",
        "Off"
      ]
    },
    {
      "pdfFieldName": "topmostSubform[0].Page2[0].Line4aChartTable[0].Line4aChartTableRow5[0].EarnedIncome[0].EarnedIncomeCalc[0].p2-t1[0]",
      "fieldType": "dollar_amount",
      "labelHint": "Dollar Amount",
      "required": false
    },
    {
      "pdfFieldName": "topmostSubform[0].Page2[0].Line4aChartTable[0].Line4aChartTableRow5[0].EarnedIncome[0].SubtractAmounts[0].p2-t2[0]",
      "fieldType": "dollar_amount",
      "labelHint": "Dollar Amount",
      "required": false
    },
    {
      "pdfFieldName": "topmostSubform[0].Page2[0].Line4aChartTable[0].Line4aChartTableRow5[0].EarnedIncome[0].AddNontaxable[0].p2-t3[0]",
      "fieldType": "dollar_amount",
      "labelHint": "Dollar Amount",
      "required": false
    },
    {
      "pdfFieldName": "topmostSubform[0].Page2[0].Line4aChartTable[0].Line4aChartTableRow5[0].EarnedIncome[0].p2-t4[0]",
      "fieldType": "dollar_amount",
      "labelHint": "Dollar Amount",
      "required": false
    }
  ]
}
